{
 "action": "Update Settings",
 "action_label": "Add API Keys",
 "creation": "2023-10-26 06:54:50.509355",
 "description": "Get your your key ID and key secret from Razorpay dashboard and add them here.",
 "docstatus": 0,
 "doctype": "Onboarding Step",
 "field": "key_id",
 "idx": 2,
 "is_complete": 0,
 "is_single": 1,
 "is_skipped": 0,
 "modified": "2023-10-26 07:01:59.955078",
 "modified_by": "Administrator",
 "name": "Set Razorpay Credentials",
 "owner": "Administrator",
 "reference_document": "Printrove Razorpay Settings",
 "show_form_tour": 0,
 "show_full_form": 0,
 "title": "Set Razorpay Credentials",
 "validate_action": 1,
 "value_to_validate": "%"
}
